textfeature/__init__.py
textfeature/mainclass.py
textfeature/module.py
textfeature/textfeature.py
textfeature-0.0.10.dist-info/LICENSE
textfeature-0.0.10.dist-info/METADATA
textfeature-0.0.10.dist-info/WHEEL
textfeature-0.0.10.dist-info/top_level.txt
textfeature-0.0.10.dist-info/RECORD
