Metadata-Version: 2.1
Name: textfeature
Version: 0.0.10
Summary: transform unstructured text to feature vector using word2vec, lexicon and ... 
Home-page: https://github.com/Farshad-Hasanpour/textfeature
Author: Farshad Hasanpour
Author-email: farshad.hasanpour96@gmail.com
License: UNKNOWN
Platform: UNKNOWN
Classifier: Programming Language :: Python :: 3
Classifier: License :: OSI Approved :: MIT License
Classifier: Operating System :: OS Independent
Requires: pandas
Requires: numpy
Requires: gensim
Requires: nltk
Requires-Python: >=3.7
